fitness/__init__.py
fitness/cli.py
fitness/py.typed
fitness-0.1.0.dist-info/METADATA
fitness-0.1.0.dist-info/WHEEL
fitness-0.1.0.dist-info/entry_points.txt
fitness-0.1.0.dist-info/licenses/LICENSE
fitness-0.1.0.dist-info/RECORD
