Metadata-Version: 2.4
Name: fitness
Version: 0.1.0
Author-email: narumi <toucans-cutouts0f@icloud.com>
License-File: LICENSE
Requires-Python: >=3.12
Requires-Dist: loguru>=0.7.3
Requires-Dist: typer>=0.20.0
